jupyter_mimetypes/__init__.py
jupyter_mimetypes/_constants.py
jupyter_mimetypes/_proxy.py
jupyter_mimetypes/_types.py
jupyter_mimetypes/_utils.py
jupyter_mimetypes/api.py
jupyter_mimetypes/_io/__init__.py
jupyter_mimetypes/_io/_api.py
jupyter_mimetypes/_io/_pandas.py
jupyter_mimetypes/_io/_pickle.py
jupyter_mimetypes-0.1.0.dist-info/METADATA
jupyter_mimetypes-0.1.0.dist-info/WHEEL
jupyter_mimetypes-0.1.0.dist-info/licenses/LICENSE
jupyter_mimetypes-0.1.0.dist-info/RECORD
